{"name":"ingresar usuario","id":"iniciar-sesion-en-store;ingresar-usuario","testSteps":[{"number":1,"description":"Dado que requiero ingresar a la pagina demoblaze","duration":15182,"startTime":"2022-02-15T00:50:45.177988200-05:00[America/Bogota]","screenshots":[{"screenshot":"fd2977fa401d91e15b7fa6828236f9d2371deda4c4b60a7c5b7d72838b1f8061.png","timeStamp":1644904260360}],"result":"SUCCESS","precondition":false,"level":0,"children":[{"number":2,"description":"Ruben abrir","duration":13668,"startTime":"2022-02-15T00:50:45.834271400-05:00[America/Bogota]","screenshots":[{"screenshot":"fd2977fa401d91e15b7fa6828236f9d2371deda4c4b60a7c5b7d72838b1f8061.png","timeStamp":1644904259502}],"result":"SUCCESS","precondition":false,"level":1,"children":[{"number":3,"description":"ruben opens the Demo blaze store home","duration":12632,"startTime":"2022-02-15T00:50:45.912398600-05:00[America/Bogota]","screenshots":[{"screenshot":"2ca978d3ec7eade581542282c48f2358445567ea415e68f7b889ab315621fae3.png","timeStamp":1644904258543}],"result":"SUCCESS","precondition":false,"level":2}]}]},{"number":4,"description":"Cuando se ingresa el usuario: ruben de jesus y contrasena: ruben123","duration":9125,"startTime":"2022-02-15T00:51:00.362791100-05:00[America/Bogota]","screenshots":[{"screenshot":"9269f15dadbbc2c956f7b65b2637524e955a6c2c7afb2394f02ce62c0ab9605a.png","timeStamp":1644904269488}],"result":"SUCCESS","precondition":false,"level":0,"children":[{"number":5,"description":"Ruben ingresar","duration":8363,"startTime":"2022-02-15T00:51:00.420329300-05:00[America/Bogota]","screenshots":[{"screenshot":"ad214af97949fe8788d09941bbe0d42bcc169dbd4f38ccd1d6efd699262699e7.png","timeStamp":1644904268783}],"result":"SUCCESS","precondition":false,"level":1,"children":[{"number":6,"description":"ruben clicks on Boton de registro","duration":2616,"startTime":"2022-02-15T00:51:01.331433400-05:00[America/Bogota]","screenshots":[{"screenshot":"7c711fb7f9aef9ce03eeaa0fb5573c6ad6d32f94c72e2f23e8dd1bb6a615da7e.png","timeStamp":1644904262317},{"screenshot":"d61188e697b74a8138d53987aed1d73e8f87fa3a41f9d048146eb05225c7199f.png","timeStamp":1644904263947}],"result":"SUCCESS","precondition":false,"level":2},{"number":7,"description":"ruben enters \u0027ruben de jesus\u0027 into input login nombre usuario","duration":1279,"startTime":"2022-02-15T00:51:03.956172500-05:00[America/Bogota]","screenshots":[{"screenshot":"d61188e697b74a8138d53987aed1d73e8f87fa3a41f9d048146eb05225c7199f.png","timeStamp":1644904263989},{"screenshot":"ae6f14e48f7669a9e40e67939b968d50d0d73606d3c93174e634adf0615d880e.png","timeStamp":1644904265235}],"result":"SUCCESS","precondition":false,"level":2},{"number":8,"description":"ruben enters \u0027ruben123\u0027 into input login password","duration":1339,"startTime":"2022-02-15T00:51:05.240023500-05:00[America/Bogota]","screenshots":[{"screenshot":"ae6f14e48f7669a9e40e67939b968d50d0d73606d3c93174e634adf0615d880e.png","timeStamp":1644904265268},{"screenshot":"f1b58c56168da7c7da178f780c3776f36291fbf4ffb10223503ff7a28fddfe65.png","timeStamp":1644904266579}],"result":"SUCCESS","precondition":false,"level":2},{"number":9,"description":"ruben clicks on Boton de registro confirmar","duration":2158,"startTime":"2022-02-15T00:51:06.594285400-05:00[America/Bogota]","screenshots":[{"screenshot":"3c935aa7a572c4490fa14262708a3a902bf10492b244b1397b8803191d9ddc46.png","timeStamp":1644904267261},{"screenshot":"ad214af97949fe8788d09941bbe0d42bcc169dbd4f38ccd1d6efd699262699e7.png","timeStamp":1644904268753}],"result":"SUCCESS","precondition":false,"level":2}]}]},{"number":10,"description":"Entonces se valida la bienvenida al usuario: ruben de jesus","duration":1623,"startTime":"2022-02-15T00:51:09.490686800-05:00[America/Bogota]","screenshots":[{"screenshot":"641f258e2d2cb5c57afa641850038d3930e90b95bac444cdb018c655a683b196.png","timeStamp":1644904271113}],"result":"SUCCESS","precondition":false,"level":0,"children":[{"number":11,"description":"Then bienvenida should be \u0027Welcome ruben de jesus\u0027","duration":1381,"startTime":"2022-02-15T00:51:09.705829100-05:00[America/Bogota]","screenshots":[{"screenshot":"641f258e2d2cb5c57afa641850038d3930e90b95bac444cdb018c655a683b196.png","timeStamp":1644904270411},{"screenshot":"641f258e2d2cb5c57afa641850038d3930e90b95bac444cdb018c655a683b196.png","timeStamp":1644904271087}],"result":"SUCCESS","precondition":false,"level":1}]}],"userStory":{"id":"iniciar-sesion-en-store","storyName":"iniciar sesion en store","path":"iniciar_sesion_Store.feature","narrative":"  Como usuario\n  quiero iniciar sesion\n  en la pagina Store","type":"feature"},"featureTag":{"name":"iniciar sesion en store","type":"feature","displayName":"iniciar sesion en store"},"title":"ingresar usuario","description":"","backgroundTitle":"","backgroundDescription":"","tags":[{"name":"iniciar sesion en store","type":"feature","displayName":"iniciar sesion en store"}],"startTime":"2022-02-15T00:50:44.646713-05:00[America/Bogota]","duration":26472,"projectKey":"","sessionId":"c9a42b361985ec3a1fa62cefe7e5cd06","driver":"chrome","isManualTestingUpToDate":false,"manual":false,"testSource":"Cucumber","actors":[{"name":"ruben","can":["browse the web"]}],"result":"SUCCESS"}